data_gateway_sdk/__init__.py
data_gateway_sdk/device_data.py
data_gateway_sdk/device_data_encryption.py
data_gateway_sdk/device_data_protocol.py
data_gateway_sdk/errors.py
data_gateway_sdk/nero_bs_protocol.py
data_gateway_sdk/py.typed
data_gateway_sdk/__tests__/__init__.py
data_gateway_sdk/__tests__/test_encryption.py
data_gateway_sdk/crypto_algorithms/__init__.py
data_gateway_sdk/crypto_algorithms/crypto_aes.py
data_gateway_sdk/crypto_algorithms/crypto_kuznechik.py
data_gateway_sdk/crypto_algorithms/crypto_xtea.py
data_gateway_sdk/crypto_algorithms/__tests__/__init__.py
data_gateway_sdk/crypto_algorithms/__tests__/crypto_test.py
data_gateway_sdk/crypto_algorithms/constants/__init__.py
data_gateway_sdk/crypto_algorithms/constants/constants_aes.py
data_gateway_sdk/crypto_algorithms/constants/constants_kuz.py
data_gateway_sdk/crypto_algorithms/constants/kuz_tables.bin
data_gateway_sdk/crypto_algorithms/extensions/__init__.py
data_gateway_sdk/crypto_algorithms/extensions/errors.py
data_gateway_sdk/crypto_algorithms/extensions/type_alias.py
data_gateway_sdk/messages/__init__.py
data_gateway_sdk/messages/input_bs_http_nero_message.py
data_gateway_sdk/protocols/__init__.py
data_gateway_sdk/protocols/device_packet/__init__.py
data_gateway_sdk/protocols/device_packet/device_packet.py
data_gateway_sdk/protocols/device_packet/ncp_smp_device_packet.py
data_gateway_sdk/protocols/device_packet/smp_device_packet.py
data_gateway_sdk/protocols/device_packet/smpm_device_packet.py
data_gateway_sdk/protocols/device_packet/water5_device_packet.py
data_gateway_sdk/protocols/device_packet/__tests__/__init__.py
data_gateway_sdk/protocols/device_packet/__tests__/test_device_protocol.py
data_gateway_sdk/protocols/nero_bs_packet/__init__.py
data_gateway_sdk/protocols/nero_bs_packet/http_nero_bs_packet.py
data_gateway_sdk/protocols/nero_bs_packet/nero_bs_packet.py
data_gateway_sdk/protocols/nero_bs_packet/__tests__/__init__.py
ul_data_gateway_sdk-1.0.9.dist-info/METADATA
ul_data_gateway_sdk-1.0.9.dist-info/WHEEL
ul_data_gateway_sdk-1.0.9.dist-info/top_level.txt
ul_data_gateway_sdk-1.0.9.dist-info/RECORD
