Metadata-Version: 2.1
Name: ul-data-gateway-sdk
Version: 1.0.9
Summary: Data gateway sdk
Author: Unic-lab
License: MIT
Platform: any
Classifier: Intended Audience :: Developers
Classifier: License :: OSI Approved :: MIT License
Classifier: Programming Language :: Python
Classifier: Programming Language :: Python :: 3.6
Classifier: Programming Language :: Python :: 3.7
Classifier: Programming Language :: Python :: 3.8
Classifier: Programming Language :: Python :: 3.9
Classifier: Operating System :: OS Independent
Requires-Dist: ul-unipipeline >=2.0.0
Requires-Dist: asyncio-dgram ==1.2.0
Requires-Dist: asyncio ==3.4.3
Requires-Dist: timezonefinder ==6.1.1
Requires-Dist: pytest-env ==0.8.1
Requires-Dist: aiormq ==6.7.7
Requires-Dist: tenacity ==8.2.3
